{"nodes": [{"id": "packages_guild_src_workflows_state_ts", "label": "state.ts", "file_type": "code", "source_file": "packages/guild/src/workflows/state.ts", "source_location": "L1"}, {"id": "state_generateresumetoken", "label": "generateResumeToken()", "file_type": "code", "source_file": "packages/guild/src/workflows/state.ts", "source_location": "L13"}, {"id": "state_sanitizeworkflowname", "label": "sanitizeWorkflowName()", "file_type": "code", "source_file": "packages/guild/src/workflows/state.ts", "source_location": "L21"}, {"id": "state_persiststate", "label": "persistState()", "file_type": "code", "source_file": "packages/guild/src/workflows/state.ts", "source_location": "L29"}, {"id": "state_loadstate", "label": "loadState()", "file_type": "code", "source_file": "packages/guild/src/workflows/state.ts", "source_location": "L64"}], "edges": [{"source": "packages_guild_src_workflows_state_ts", "target": "fs", "relation": "imports_from", "confidence": "EXTRACTED", "source_file": "packages/guild/src/workflows/state.ts", "source_location": "L5", "weight": 1.0}, {"source": "packages_guild_src_workflows_state_ts", "target": "path", "relation": "imports_from", "confidence": "EXTRACTED", "source_file": "packages/guild/src/workflows/state.ts", "source_location": "L6", "weight": 1.0}, {"source": "packages_guild_src_workflows_state_ts", "target": "crypto", "relation": "imports_from", "confidence": "EXTRACTED", "source_file": "packages/guild/src/workflows/state.ts", "source_location": "L7", "weight": 1.0}, {"source": "packages_guild_src_workflows_state_ts", "target": "packages_guild_src_workflows_types_ts", "relation": "imports_from", "confidence": "EXTRACTED", "source_file": "packages/guild/src/workflows/state.ts", "source_location": "L8", "weight": 1.0}, {"source": "packages_guild_src_workflows_state_ts", "target": "state_generateresumetoken", "relation": "contains", "confidence": "EXTRACTED", "source_file": "packages/guild/src/workflows/state.ts", "source_location": "L13", "weight": 1.0}, {"source": "packages_guild_src_workflows_state_ts", "target": "state_sanitizeworkflowname", "relation": "contains", "confidence": "EXTRACTED", "source_file": "packages/guild/src/workflows/state.ts", "source_location": "L21", "weight": 1.0}, {"source": "packages_guild_src_workflows_state_ts", "target": "state_persiststate", "relation": "contains", "confidence": "EXTRACTED", "source_file": "packages/guild/src/workflows/state.ts", "source_location": "L29", "weight": 1.0}, {"source": "packages_guild_src_workflows_state_ts", "target": "state_loadstate", "relation": "contains", "confidence": "EXTRACTED", "source_file": "packages/guild/src/workflows/state.ts", "source_location": "L64", "weight": 1.0}, {"source": "state_persiststate", "target": "state_sanitizeworkflowname", "relation": "calls", "confidence": "EXTRACTED", "source_file": "packages/guild/src/workflows/state.ts", "source_location": "L45", "weight": 1.0}]}