{"nodes": [{"id": "packages_summon_src_skills_installer_ts", "label": "installer.ts", "file_type": "code", "source_file": "packages/summon/src/skills/installer.ts", "source_location": "L1"}, {"id": "installer_ispathwithin", "label": "isPathWithin()", "file_type": "code", "source_file": "packages/summon/src/skills/installer.ts", "source_location": "L22"}, {"id": "installer_issymlinktargetsafe", "label": "isSymlinkTargetSafe()", "file_type": "code", "source_file": "packages/summon/src/skills/installer.ts", "source_location": "L30"}, {"id": "installer_gethubskillpath", "label": "getHubSkillPath()", "file_type": "code", "source_file": "packages/summon/src/skills/installer.ts", "source_location": "L50"}, {"id": "installer_computerelativepath", "label": "computeRelativePath()", "file_type": "code", "source_file": "packages/summon/src/skills/installer.ts", "source_location": "L65"}, {"id": "installer_createhubsymlink", "label": "createHubSymlink()", "file_type": "code", "source_file": "packages/summon/src/skills/installer.ts", "source_location": "L74"}, {"id": "installer_validateskillsource", "label": "validateSkillSource()", "file_type": "code", "source_file": "packages/summon/src/skills/installer.ts", "source_location": "L105"}, {"id": "installer_resolveinstalltarget", "label": "resolveInstallTarget()", "file_type": "code", "source_file": "packages/summon/src/skills/installer.ts", "source_location": "L123"}, {"id": "installer_createhubsymlinkorerror", "label": "createHubSymlinkOrError()", "file_type": "code", "source_file": "packages/summon/src/skills/installer.ts", "source_location": "L142"}, {"id": "installer_linkagentskill", "label": "linkAgentSkill()", "file_type": "code", "source_file": "packages/summon/src/skills/installer.ts", "source_location": "L160"}, {"id": "installer_resulterror", "label": "resultError()", "file_type": "code", "source_file": "packages/summon/src/skills/installer.ts", "source_location": "L174"}, {"id": "installer_resultsuccess", "label": "resultSuccess()", "file_type": "code", "source_file": "packages/summon/src/skills/installer.ts", "source_location": "L183"}, {"id": "installer_createskillsymlink", "label": "createSkillSymlink()", "file_type": "code", "source_file": "packages/summon/src/skills/installer.ts", "source_location": "L191"}, {"id": "installer_installskill", "label": "installSkill()", "file_type": "code", "source_file": "packages/summon/src/skills/installer.ts", "source_location": "L205"}, {"id": "installer_removeskill", "label": "removeSkill()", "file_type": "code", "source_file": "packages/summon/src/skills/installer.ts", "source_location": "L234"}, {"id": "installer_validateupdatetarget", "label": "validateUpdateTarget()", "file_type": "code", "source_file": "packages/summon/src/skills/installer.ts", "source_location": "L257"}, {"id": "installer_healsymlinkchain", "label": "healSymlinkChain()", "file_type": "code", "source_file": "packages/summon/src/skills/installer.ts", "source_location": "L272"}, {"id": "installer_updateskill", "label": "updateSkill()", "file_type": "code", "source_file": "packages/summon/src/skills/installer.ts", "source_location": "L306"}], "edges": [{"source": "packages_summon_src_skills_installer_ts", "target": "node_path", "relation": "imports_from", "confidence": "EXTRACTED", "source_file": "packages/summon/src/skills/installer.ts", "source_location": "L1", "weight": 1.0}, {"source": "packages_summon_src_skills_installer_ts", "target": "promises", "relation": "imports_from", "confidence": "EXTRACTED", "source_file": "packages/summon/src/skills/installer.ts", "source_location": "L2", "weight": 1.0}, {"source": "packages_summon_src_skills_installer_ts", "target": "packages_summon_src_skills_utils_fs", "relation": "imports_from", "confidence": "EXTRACTED", "source_file": "packages/summon/src/skills/installer.ts", "source_location": "L3", "weight": 1.0}, {"source": "packages_summon_src_skills_installer_ts", "target": "packages_summon_src_skills_constants", "relation": "imports_from", "confidence": "EXTRACTED", "source_file": "packages/summon/src/skills/installer.ts", "source_location": "L11", "weight": 1.0}, {"source": "packages_summon_src_skills_installer_ts", "target": "packages_summon_src_skills_utils_paths", "relation": "imports_from", "confidence": "EXTRACTED", "source_file": "packages/summon/src/skills/installer.ts", "source_location": "L12", "weight": 1.0}, {"source": "packages_summon_src_skills_installer_ts", "target": "packages_summon_src_skills_loader", "relation": "imports_from", "confidence": "EXTRACTED", "source_file": "packages/summon/src/skills/installer.ts", "source_location": "L13", "weight": 1.0}, {"source": "packages_summon_src_skills_installer_ts", "target": "packages_summon_src_skills_utils_paths", "relation": "imports_from", "confidence": "EXTRACTED", "source_file": "packages/summon/src/skills/installer.ts", "source_location": "L14", "weight": 1.0}, {"source": "packages_summon_src_skills_installer_ts", "target": "installer_ispathwithin", "relation": "contains", "confidence": "EXTRACTED", "source_file": "packages/summon/src/skills/installer.ts", "source_location": "L22", "weight": 1.0}, {"source": "packages_summon_src_skills_installer_ts", "target": "installer_issymlinktargetsafe", "relation": "contains", "confidence": "EXTRACTED", "source_file": "packages/summon/src/skills/installer.ts", "source_location": "L30", "weight": 1.0}, {"source": "packages_summon_src_skills_installer_ts", "target": "installer_gethubskillpath", "relation": "contains", "confidence": "EXTRACTED", "source_file": "packages/summon/src/skills/installer.ts", "source_location": "L50", "weight": 1.0}, {"source": "packages_summon_src_skills_installer_ts", "target": "installer_computerelativepath", "relation": "contains", "confidence": "EXTRACTED", "source_file": "packages/summon/src/skills/installer.ts", "source_location": "L65", "weight": 1.0}, {"source": "packages_summon_src_skills_installer_ts", "target": "installer_createhubsymlink", "relation": "contains", "confidence": "EXTRACTED", "source_file": "packages/summon/src/skills/installer.ts", "source_location": "L74", "weight": 1.0}, {"source": "packages_summon_src_skills_installer_ts", "target": "installer_validateskillsource", "relation": "contains", "confidence": "EXTRACTED", "source_file": "packages/summon/src/skills/installer.ts", "source_location": "L105", "weight": 1.0}, {"source": "packages_summon_src_skills_installer_ts", "target": "installer_resolveinstalltarget", "relation": "contains", "confidence": "EXTRACTED", "source_file": "packages/summon/src/skills/installer.ts", "source_location": "L123", "weight": 1.0}, {"source": "packages_summon_src_skills_installer_ts", "target": "installer_createhubsymlinkorerror", "relation": "contains", "confidence": "EXTRACTED", "source_file": "packages/summon/src/skills/installer.ts", "source_location": "L142", "weight": 1.0}, {"source": "packages_summon_src_skills_installer_ts", "target": "installer_linkagentskill", "relation": "contains", "confidence": "EXTRACTED", "source_file": "packages/summon/src/skills/installer.ts", "source_location": "L160", "weight": 1.0}, {"source": "packages_summon_src_skills_installer_ts", "target": "installer_resulterror", "relation": "contains", "confidence": "EXTRACTED", "source_file": "packages/summon/src/skills/installer.ts", "source_location": "L174", "weight": 1.0}, {"source": "packages_summon_src_skills_installer_ts", "target": "installer_resultsuccess", "relation": "contains", "confidence": "EXTRACTED", "source_file": "packages/summon/src/skills/installer.ts", "source_location": "L183", "weight": 1.0}, {"source": "packages_summon_src_skills_installer_ts", "target": "installer_createskillsymlink", "relation": "contains", "confidence": "EXTRACTED", "source_file": "packages/summon/src/skills/installer.ts", "source_location": "L191", "weight": 1.0}, {"source": "packages_summon_src_skills_installer_ts", "target": "installer_installskill", "relation": "contains", "confidence": "EXTRACTED", "source_file": "packages/summon/src/skills/installer.ts", "source_location": "L205", "weight": 1.0}, {"source": "packages_summon_src_skills_installer_ts", "target": "installer_removeskill", "relation": "contains", "confidence": "EXTRACTED", "source_file": "packages/summon/src/skills/installer.ts", "source_location": "L234", "weight": 1.0}, {"source": "packages_summon_src_skills_installer_ts", "target": "installer_validateupdatetarget", "relation": "contains", "confidence": "EXTRACTED", "source_file": "packages/summon/src/skills/installer.ts", "source_location": "L257", "weight": 1.0}, {"source": "packages_summon_src_skills_installer_ts", "target": "installer_healsymlinkchain", "relation": "contains", "confidence": "EXTRACTED", "source_file": "packages/summon/src/skills/installer.ts", "source_location": "L272", "weight": 1.0}, {"source": "packages_summon_src_skills_installer_ts", "target": "installer_updateskill", "relation": "contains", "confidence": "EXTRACTED", "source_file": "packages/summon/src/skills/installer.ts", "source_location": "L306", "weight": 1.0}, {"source": "installer_issymlinktargetsafe", "target": "installer_ispathwithin", "relation": "calls", "confidence": "EXTRACTED", "source_file": "packages/summon/src/skills/installer.ts", "source_location": "L33", "weight": 1.0}, {"source": "installer_createhubsymlink", "target": "installer_computerelativepath", "relation": "calls", "confidence": "EXTRACTED", "source_file": "packages/summon/src/skills/installer.ts", "source_location": "L86", "weight": 1.0}, {"source": "installer_resolveinstalltarget", "target": "installer_ispathwithin", "relation": "calls", "confidence": "EXTRACTED", "source_file": "packages/summon/src/skills/installer.ts", "source_location": "L130", "weight": 1.0}, {"source": "installer_createhubsymlinkorerror", "target": "installer_createhubsymlink", "relation": "calls", "confidence": "EXTRACTED", "source_file": "packages/summon/src/skills/installer.ts", "source_location": "L147", "weight": 1.0}, {"source": "installer_linkagentskill", "target": "installer_computerelativepath", "relation": "calls", "confidence": "EXTRACTED", "source_file": "packages/summon/src/skills/installer.ts", "source_location": "L167", "weight": 1.0}, {"source": "installer_createskillsymlink", "target": "installer_resulterror", "relation": "calls", "confidence": "EXTRACTED", "source_file": "packages/summon/src/skills/installer.ts", "source_location": "L197", "weight": 1.0}, {"source": "installer_createskillsymlink", "target": "installer_createhubsymlinkorerror", "relation": "calls", "confidence": "EXTRACTED", "source_file": "packages/summon/src/skills/installer.ts", "source_location": "L199", "weight": 1.0}, {"source": "installer_createskillsymlink", "target": "installer_linkagentskill", "relation": "calls", "confidence": "EXTRACTED", "source_file": "packages/summon/src/skills/installer.ts", "source_location": "L201", "weight": 1.0}, {"source": "installer_installskill", "target": "installer_validateskillsource", "relation": "calls", "confidence": "EXTRACTED", "source_file": "packages/summon/src/skills/installer.ts", "source_location": "L216", "weight": 1.0}, {"source": "installer_installskill", "target": "installer_resolveinstalltarget", "relation": "calls", "confidence": "EXTRACTED", "source_file": "packages/summon/src/skills/installer.ts", "source_location": "L218", "weight": 1.0}, {"source": "installer_installskill", "target": "installer_gethubskillpath", "relation": "calls", "confidence": "EXTRACTED", "source_file": "packages/summon/src/skills/installer.ts", "source_location": "L222", "weight": 1.0}, {"source": "installer_installskill", "target": "installer_createskillsymlink", "relation": "calls", "confidence": "EXTRACTED", "source_file": "packages/summon/src/skills/installer.ts", "source_location": "L223", "weight": 1.0}, {"source": "installer_installskill", "target": "installer_resultsuccess", "relation": "calls", "confidence": "EXTRACTED", "source_file": "packages/summon/src/skills/installer.ts", "source_location": "L228", "weight": 1.0}, {"source": "installer_installskill", "target": "installer_resulterror", "relation": "calls", "confidence": "EXTRACTED", "source_file": "packages/summon/src/skills/installer.ts", "source_location": "L230", "weight": 1.0}, {"source": "installer_removeskill", "target": "installer_gethubskillpath", "relation": "calls", "confidence": "EXTRACTED", "source_file": "packages/summon/src/skills/installer.ts", "source_location": "L243", "weight": 1.0}, {"source": "installer_removeskill", "target": "installer_resultsuccess", "relation": "calls", "confidence": "EXTRACTED", "source_file": "packages/summon/src/skills/installer.ts", "source_location": "L251", "weight": 1.0}, {"source": "installer_removeskill", "target": "installer_resulterror", "relation": "calls", "confidence": "EXTRACTED", "source_file": "packages/summon/src/skills/installer.ts", "source_location": "L253", "weight": 1.0}, {"source": "installer_healsymlinkchain", "target": "installer_createhubsymlink", "relation": "calls", "confidence": "EXTRACTED", "source_file": "packages/summon/src/skills/installer.ts", "source_location": "L280", "weight": 1.0}, {"source": "installer_healsymlinkchain", "target": "installer_computerelativepath", "relation": "calls", "confidence": "EXTRACTED", "source_file": "packages/summon/src/skills/installer.ts", "source_location": "L296", "weight": 1.0}, {"source": "installer_updateskill", "target": "installer_validateupdatetarget", "relation": "calls", "confidence": "EXTRACTED", "source_file": "packages/summon/src/skills/installer.ts", "source_location": "L318", "weight": 1.0}, {"source": "installer_updateskill", "target": "installer_gethubskillpath", "relation": "calls", "confidence": "EXTRACTED", "source_file": "packages/summon/src/skills/installer.ts", "source_location": "L320", "weight": 1.0}, {"source": "installer_updateskill", "target": "installer_healsymlinkchain", "relation": "calls", "confidence": "EXTRACTED", "source_file": "packages/summon/src/skills/installer.ts", "source_location": "L322", "weight": 1.0}, {"source": "installer_updateskill", "target": "installer_resultsuccess", "relation": "calls", "confidence": "EXTRACTED", "source_file": "packages/summon/src/skills/installer.ts", "source_location": "L324", "weight": 1.0}, {"source": "installer_updateskill", "target": "installer_installskill", "relation": "calls", "confidence": "EXTRACTED", "source_file": "packages/summon/src/skills/installer.ts", "source_location": "L327", "weight": 1.0}, {"source": "installer_updateskill", "target": "installer_resulterror", "relation": "calls", "confidence": "EXTRACTED", "source_file": "packages/summon/src/skills/installer.ts", "source_location": "L330", "weight": 1.0}]}